lufah/__init__.py
lufah/__main__.py
lufah/cli_typer.py
lufah/const.py
lufah/exceptions.py
lufah/fahclient.py
lufah/logger.py
lufah/updatable.py
lufah/util.py
lufah/validate.py
lufah/commands/__init__.py
lufah/commands/config.py
lufah/commands/core/__init__.py
lufah/commands/core/config.py
lufah/commands/core/create_group.py
lufah/commands/core/dump_all.py
lufah/commands/core/enable_all_gpus.py
lufah/commands/core/finish_fold_pause.py
lufah/commands/core/get.py
lufah/commands/core/groups.py
lufah/commands/core/history.py
lufah/commands/core/info.py
lufah/commands/core/link_account.py
lufah/commands/core/log.py
lufah/commands/core/not_implemented.py
lufah/commands/core/restart_account.py
lufah/commands/core/start_stop.py
lufah/commands/core/state.py
lufah/commands/core/top.py
lufah/commands/core/units.py
lufah/commands/core/unlink_account.py
lufah/commands/core/wait_until_paused.py
lufah/commands/core/watch.py
lufah-0.11.0.dist-info/METADATA
lufah-0.11.0.dist-info/WHEEL
lufah-0.11.0.dist-info/entry_points.txt
lufah-0.11.0.dist-info/licenses/LICENSE
lufah-0.11.0.dist-info/RECORD
