Metadata-Version: 2.4
Name: lufah
Version: 0.11.0
Summary: Command line utility for controlling foldingathome version 8
Project-URL: Homepage, https://github.com/kbernhagen/lufah
Project-URL: Changelog, https://github.com/kbernhagen/lufah/blob/main/CHANGELOG.md
Author-email: Kevin Bernhagen <kbernhagen.github@gmail.com>
License: MIT License
License-File: LICENSE
Keywords: fah,folding-at-home,folding@home,foldingathome
Classifier: Development Status :: 3 - Alpha
Classifier: Environment :: Console
Classifier: License :: OSI Approved :: MIT License
Classifier: Natural Language :: English
Classifier: Operating System :: OS Independent
Classifier: Programming Language :: Python :: 3
Classifier: Programming Language :: Python :: 3.9
Classifier: Programming Language :: Python :: 3.10
Classifier: Programming Language :: Python :: 3.11
Classifier: Programming Language :: Python :: 3.12
Requires-Python: >=3.9
Requires-Dist: shellingham
Requires-Dist: tabulate2>=1.9.2
Requires-Dist: typer-slim
Requires-Dist: websockets>=13.0.1
